senpy_club-0.1.1.dist-info/METADATA
senpy_club-0.1.1.dist-info/WHEEL
senpy_club/__init__.py
senpy_club/senpy_club.cp310-win_amd64.pyd
senpy_club-0.1.1.dist-info/RECORD
