Metadata-Version: 2.1
Name: senpy-club
Version: 0.1.1
Summary: The Senpy Club API Wrapper for Python
Keywords: rust,anime,senpy,senpy-club
Home-Page: https://pypi.org/project/senpy-club/
Author: Fuwn <fuwnzy@gmail.com>
Author-email: Fuwn <fuwnzy@gmail.com>
License: GPL-3.0-only
Project-URL: Source Code, https://github.com/senpy-club/sen-py
